skai/__init__.py
skai/base/__init__.py
skai/base/llm/__init__.py
skai/base/rl/__init__.py
skai/base/rl/_base.py
skai/llm/__init__.py
skai/llm/_openai.py
skai/py.typed
scikit_ai-0.1.0.dist-info/WHEEL
scikit_ai-0.1.0.dist-info/METADATA
scikit_ai-0.1.0.dist-info/licenses/LICENSE
scikit_ai-0.1.0.dist-info/RECORD
