Metadata-Version: 2.1
Name: scikit-ai
Version: 0.1.0
Summary: A unified AI library that brings together classical Machine Learning, Reinforcement Learning, and Large Language Models under a consistent and simple interface.
License: MIT
Author-email: Georgios Douzas <gdouzas@icloud.com>
Requires-Python: >=3.11, <3.14
Classifier: Development Status :: 4 - Beta
Classifier: Intended Audience :: Developers
Classifier: Programming Language :: Python
Classifier: Programming Language :: Python :: 3
Classifier: Programming Language :: Python :: 3 :: Only
Classifier: Programming Language :: Python :: 3.11
Classifier: Programming Language :: Python :: 3.12
Classifier: Programming Language :: Python :: 3.13
Classifier: Topic :: Documentation
Classifier: Topic :: Software Development
Classifier: Topic :: Utilities
Classifier: Typing :: Typed
Requires-Dist: openai>=1.82.0
Requires-Dist: python-dotenv>=1.1.0
Requires-Dist: scikit-learn>=1.5.2
Project-URL: Changelog, https://georgedouzas.github.io/scikit-ai/changelog
Project-URL: Discussions, https://github.com/georgedouzas/scikit-ai/discussions
Project-URL: Documentation, https://georgedouzas.github.io/scikit-ai
Project-URL: Funding, https://github.com/sponsors/georgedouzas
Project-URL: Gitter, https://gitter.im/scikit-ai/community
Project-URL: Homepage, https://georgedouzas.github.io/scikit-ai
Project-URL: Issues, https://github.com/georgedouzas/scikit-ai/issues
Project-URL: Repository, https://github.com/georgedouzas/scikit-ai
